{"devicePlatform":"","logFolder":"C:\\Users\\Zahir\\Katalon Studio\\MyHours_Assignment\\Reports\\MyHours_TestSuite\\20180626_211207","runData":{"hostName":"Zahir - DESKTOP-DH2KCP9.lan","os":"Windows 10 64bit","katalonVersion":"5.3.0.1","browser":"Firefox 60.0","hostAddress":"192.168.1.80","sessionId":"787a5e1d-345f-4355-858f-b459287f4a1f","seleniumVersion":"3.7.1","proxyInformation":"ProxyInformation{proxyOption\u003dNO_PROXY, proxyServerType\u003dHTTP, password\u003d, proxyServerAddress\u003d, proxyServerPort\u003d0}","platform":"Windows 10"},"type":"TEST_SUITE","name":"MyHours_TestSuite","id":"Test Suites/MyHours_TestSuite","source":"","message":"Test Cases/TrackActivity/NewActivity_TestCase FAILED because (of) Unable to click on object \u0027Object Repository/NewActivity_Object_Repository/textarea_form-control ng-untou\u0027 (Root cause: com.kms.katalon.core.webui.exception.WebElementNotFoundException: Web element with id: \u0027Object Repository/NewActivity_Object_Repository/textarea_form-control ng-untou\u0027 located by \u0027By.xpath: //*[@class \u003d \u0027form-control ng-untouched ng-valid ng-dirty ng-valid-parse\u0027]\u0027 not found)","description":"","startTime":1530036730178,"endTime":1530036778020,"childRecords":[{"isOptional":false,"type":"TEST_CASE","name":"Test Cases/Login/Login_TestCase","id":"Test Cases/Login/Login_TestCase","source":"C:\\\\Users\\\\Zahir\\\\Katalon Studio\\\\MyHours_Assignment\\\\Test Cases\\\\Login\\\\Login_TestCase.tc","message":"Test Cases/Login/Login_TestCase","description":"","startTime":1530036731008,"endTime":1530036741921,"childRecords":[{"testStatus":{"stackTrace":"","statusValue":"INFO"},"type":"MESSAGE","name":"","message":"Evaluating variables for test case","startTime":1530036731103,"endTime":0,"childRecords":[],"interuppted":false},{"testStatus":{"stackTrace":"","statusValue":"INFO"},"type":"MESSAGE","name":"","message":"Variable \u0027varUserName\u0027 is set to zaheeeb@gmail.com","startTime":1530036731121,"endTime":0,"childRecords":[],"interuppted":false},{"testStatus":{"stackTrace":"","statusValue":"INFO"},"type":"MESSAGE","name":"","message":"Variable \u0027varPassword\u0027 is set to *********","startTime":1530036731123,"endTime":0,"childRecords":[],"interuppted":false},{"index":1,"isIgnoredIfFailed":false,"type":"TEST_STEP","name":"openBrowser","message":"Browser is opened with url: \u0027\u0027","description":"","startTime":1530036731619,"endTime":1530036737274,"childRecords":[{"testStatus":{"stackTrace":"","statusValue":"PASSED"},"type":"MESSAGE","name":"","message":"Browser is opened with url: \u0027\u0027","startTime":1530036737273,"endTime":0,"childRecords":[],"interuppted":false}],"interuppted":false},{"index":2,"isIgnoredIfFailed":false,"type":"TEST_STEP","name":"navigateToUrl","message":"Navigate to \u0027https://app.myhours.com/#/signin\u0027 successfully","description":"","startTime":1530036737274,"endTime":1530036741199,"childRecords":[{"testStatus":{"stackTrace":"","statusValue":"PASSED"},"type":"MESSAGE","name":"","message":"Navigate to \u0027https://app.myhours.com/#/signin\u0027 successfully","startTime":1530036741198,"endTime":0,"childRecords":[],"interuppted":false}],"interuppted":false},{"index":3,"isIgnoredIfFailed":false,"type":"TEST_STEP","name":"waitForElementVisible","message":"Object \u0027Object Repository/Login_Object_Repository/input_email\u0027 is visible","description":"","startTime":1530036741199,"endTime":1530036741363,"childRecords":[{"testStatus":{"stackTrace":"","statusValue":"PASSED"},"type":"MESSAGE","name":"","message":"Object \u0027Object Repository/Login_Object_Repository/input_email\u0027 is visible","startTime":1530036741362,"endTime":0,"childRecords":[],"interuppted":false}],"interuppted":false},{"index":4,"isIgnoredIfFailed":false,"type":"TEST_STEP","name":"setText","message":"Text \u0027zaheeeb@gmail.com\u0027 is set on object \u0027Object Repository/Login_Object_Repository/input_email\u0027","description":"","startTime":1530036741363,"endTime":1530036741646,"childRecords":[{"testStatus":{"stackTrace":"","statusValue":"PASSED"},"type":"MESSAGE","name":"","message":"Text \u0027zaheeeb@gmail.com\u0027 is set on object \u0027Object Repository/Login_Object_Repository/input_email\u0027","startTime":1530036741645,"endTime":0,"childRecords":[],"interuppted":false}],"interuppted":false},{"index":5,"isIgnoredIfFailed":false,"type":"TEST_STEP","name":"setText","message":"Text \u0027test12345\u0027 is set on object \u0027Object Repository/Login_Object_Repository/input_password\u0027","description":"","startTime":1530036741647,"endTime":1530036741791,"childRecords":[{"testStatus":{"stackTrace":"","statusValue":"PASSED"},"type":"MESSAGE","name":"","message":"Text \u0027test12345\u0027 is set on object \u0027Object Repository/Login_Object_Repository/input_password\u0027","startTime":1530036741790,"endTime":0,"childRecords":[],"interuppted":false}],"interuppted":false},{"index":6,"isIgnoredIfFailed":false,"type":"TEST_STEP","name":"sendKeys","message":"Keys \u0027ENTER + \u0027 sent to object: \u0027Object Repository/Login_Object_Repository/input_password\u0027","description":"","startTime":1530036741791,"endTime":1530036741919,"childRecords":[{"testStatus":{"stackTrace":"","statusValue":"PASSED"},"type":"MESSAGE","name":"","message":"Keys \u0027ENTER + \u0027 sent to object: \u0027Object Repository/Login_Object_Repository/input_password\u0027","startTime":1530036741917,"endTime":0,"childRecords":[],"interuppted":false}],"interuppted":false},{"testStatus":{"stackTrace":"","statusValue":"PASSED"},"type":"MESSAGE","name":"","message":"Test Cases/Login/Login_TestCase","startTime":1530036741920,"endTime":0,"childRecords":[],"interuppted":false}],"interuppted":false},{"isOptional":false,"type":"TEST_CASE","name":"Test Cases/TrackActivity/NewActivity_TestCase","id":"Test Cases/TrackActivity/NewActivity_TestCase","source":"C:\\\\Users\\\\Zahir\\\\Katalon Studio\\\\MyHours_Assignment\\\\Test Cases\\\\TrackActivity\\\\NewActivity_TestCase.tc","message":"Test Cases/TrackActivity/NewActivity_TestCase FAILED because (of) Unable to click on object \u0027Object Repository/NewActivity_Object_Repository/textarea_form-control ng-untou\u0027 (Root cause: com.kms.katalon.core.webui.exception.WebElementNotFoundException: Web element with id: \u0027Object Repository/NewActivity_Object_Repository/textarea_form-control ng-untou\u0027 located by \u0027By.xpath: //*[@class \u003d \u0027form-control ng-untouched ng-valid ng-dirty ng-valid-parse\u0027]\u0027 not found)","description":"","startTime":1530036741926,"endTime":1530036777648,"childRecords":[{"testStatus":{"stackTrace":"","statusValue":"INFO"},"type":"MESSAGE","name":"","message":"Evaluating variables for test case","startTime":1530036741953,"endTime":0,"childRecords":[],"interuppted":false},{"testStatus":{"stackTrace":"","statusValue":"INFO"},"type":"MESSAGE","name":"","message":"Variable \u0027startTime\u0027 is set to 01:00 as default","startTime":1530036742158,"endTime":0,"childRecords":[],"interuppted":false},{"index":1,"isIgnoredIfFailed":false,"type":"TEST_STEP","name":"click","message":"Object: \u0027Object Repository/NewActivity_Object_Repository/i_caret pull-right\u0027 is clicked on","description":"","startTime":1530036742430,"endTime":1530036744349,"childRecords":[{"testStatus":{"stackTrace":"","statusValue":"PASSED"},"type":"MESSAGE","name":"","message":"Object: \u0027Object Repository/NewActivity_Object_Repository/i_caret pull-right\u0027 is clicked on","startTime":1530036744348,"endTime":0,"childRecords":[],"interuppted":false}],"interuppted":false},{"index":2,"isIgnoredIfFailed":false,"type":"TEST_STEP","name":"click","message":"Object: \u0027Object Repository/NewActivity_Object_Repository/span_Project\u0027 is clicked on","description":"","startTime":1530036744349,"endTime":1530036744848,"childRecords":[{"testStatus":{"stackTrace":"","statusValue":"PASSED"},"type":"MESSAGE","name":"","message":"Object: \u0027Object Repository/NewActivity_Object_Repository/span_Project\u0027 is clicked on","startTime":1530036744847,"endTime":0,"childRecords":[],"interuppted":false}],"interuppted":false},{"index":3,"isIgnoredIfFailed":false,"type":"TEST_STEP","name":"click","message":"Object: \u0027Object Repository/NewActivity_Object_Repository/i_caret pull-right_1\u0027 is clicked on","description":"","startTime":1530036744848,"endTime":1530036745303,"childRecords":[{"testStatus":{"stackTrace":"","statusValue":"PASSED"},"type":"MESSAGE","name":"","message":"Object: \u0027Object Repository/NewActivity_Object_Repository/i_caret pull-right_1\u0027 is clicked on","startTime":1530036745302,"endTime":0,"childRecords":[],"interuppted":false}],"interuppted":false},{"index":4,"isIgnoredIfFailed":false,"type":"TEST_STEP","name":"click","message":"Object: \u0027Object Repository/NewActivity_Object_Repository/span_Meeting With Client\u0027 is clicked on","description":"","startTime":1530036745303,"endTime":1530036745779,"childRecords":[{"testStatus":{"stackTrace":"","statusValue":"PASSED"},"type":"MESSAGE","name":"","message":"Object: \u0027Object Repository/NewActivity_Object_Repository/span_Meeting With Client\u0027 is clicked on","startTime":1530036745779,"endTime":0,"childRecords":[],"interuppted":false}],"interuppted":false},{"index":5,"isIgnoredIfFailed":false,"type":"TEST_STEP","name":"waitForElementPresent","message":"Object \u0027Object Repository/NewActivity_Object_Repository/input_form-control ng-pristine\u0027 is present","description":"","startTime":1530036745779,"endTime":1530036745823,"childRecords":[{"testStatus":{"stackTrace":"","statusValue":"PASSED"},"type":"MESSAGE","name":"","message":"Object \u0027Object Repository/NewActivity_Object_Repository/input_form-control ng-pristine\u0027 is present","startTime":1530036745823,"endTime":0,"childRecords":[],"interuppted":false}],"interuppted":false},{"index":6,"isIgnoredIfFailed":false,"type":"TEST_STEP","name":"click","message":"Object: \u0027Object Repository/NewActivity_Object_Repository/input_form-control ng-pristine\u0027 is clicked on","description":"","startTime":1530036745823,"endTime":1530036746103,"childRecords":[{"testStatus":{"stackTrace":"","statusValue":"PASSED"},"type":"MESSAGE","name":"","message":"Object: \u0027Object Repository/NewActivity_Object_Repository/input_form-control ng-pristine\u0027 is clicked on","startTime":1530036746100,"endTime":0,"childRecords":[],"interuppted":false}],"interuppted":false},{"index":7,"isIgnoredIfFailed":false,"type":"TEST_STEP","name":"setText","message":"Text \u002701:00\u0027 is set on object \u0027Object Repository/NewActivity_Object_Repository/input_form-control ng-pristine\u0027","description":"","startTime":1530036746104,"endTime":1530036746161,"childRecords":[{"testStatus":{"stackTrace":"","statusValue":"PASSED"},"type":"MESSAGE","name":"","message":"Text \u002701:00\u0027 is set on object \u0027Object Repository/NewActivity_Object_Repository/input_form-control ng-pristine\u0027","startTime":1530036746161,"endTime":0,"childRecords":[],"interuppted":false}],"interuppted":false},{"index":8,"isIgnoredIfFailed":false,"type":"TEST_STEP","name":"click","message":"Object: \u0027Object Repository/NewActivity_Object_Repository/input_form-control ng-pristine\u0027 is clicked on","description":"","startTime":1530036746162,"endTime":1530036746419,"childRecords":[{"testStatus":{"stackTrace":"","statusValue":"PASSED"},"type":"MESSAGE","name":"","message":"Object: \u0027Object Repository/NewActivity_Object_Repository/input_form-control ng-pristine\u0027 is clicked on","startTime":1530036746414,"endTime":0,"childRecords":[],"interuppted":false}],"interuppted":false},{"index":9,"isIgnoredIfFailed":false,"type":"TEST_STEP","name":"setText","message":"Text \u002702\u0027 is set on object \u0027Object Repository/NewActivity_Object_Repository/input_form-control ng-pristine\u0027","description":"","startTime":1530036746421,"endTime":1530036746544,"childRecords":[{"testStatus":{"stackTrace":"","statusValue":"PASSED"},"type":"MESSAGE","name":"","message":"Text \u002702\u0027 is set on object \u0027Object Repository/NewActivity_Object_Repository/input_form-control ng-pristine\u0027","startTime":1530036746543,"endTime":0,"childRecords":[],"interuppted":false}],"interuppted":false},{"index":10,"isIgnoredIfFailed":false,"type":"TEST_STEP","name":"setText","message":"Text \u002710\u0027 is set on object \u0027Object Repository/NewActivity_Object_Repository/input_addCost\u0027","description":"","startTime":1530036746544,"endTime":1530036746700,"childRecords":[{"testStatus":{"stackTrace":"","statusValue":"PASSED"},"type":"MESSAGE","name":"","message":"Text \u002710\u0027 is set on object \u0027Object Repository/NewActivity_Object_Repository/input_addCost\u0027","startTime":1530036746699,"endTime":0,"childRecords":[],"interuppted":false}],"interuppted":false},{"attachment":"1530036777391.png","index":11,"isIgnoredIfFailed":false,"type":"TEST_STEP","name":"click","message":"Unable to click on object \u0027Object Repository/NewActivity_Object_Repository/textarea_form-control ng-untou\u0027 (Root cause: com.kms.katalon.core.webui.exception.WebElementNotFoundException: Web element with id: \u0027Object Repository/NewActivity_Object_Repository/textarea_form-control ng-untou\u0027 located by \u0027By.xpath: //*[@class \u003d \u0027form-control ng-untouched ng-valid ng-dirty ng-valid-parse\u0027]\u0027 not found)","description":"","startTime":1530036746701,"endTime":1530036777647,"childRecords":[{"testStatus":{"stackTrace":"","statusValue":"FAILED"},"attachment":"1530036777391.png","type":"MESSAGE","name":"","message":"Unable to click on object \u0027Object Repository/NewActivity_Object_Repository/textarea_form-control ng-untou\u0027 (Root cause: com.kms.katalon.core.webui.exception.WebElementNotFoundException: Web element with id: \u0027Object Repository/NewActivity_Object_Repository/textarea_form-control ng-untou\u0027 located by \u0027By.xpath: //*[@class \u003d \u0027form-control ng-untouched ng-valid ng-dirty ng-valid-parse\u0027]\u0027 not found)","startTime":1530036777647,"endTime":0,"childRecords":[],"interuppted":false}],"interuppted":false},{"testStatus":{"stackTrace":"","statusValue":"FAILED"},"type":"MESSAGE","name":"","message":"Test Cases/TrackActivity/NewActivity_TestCase FAILED because (of) Unable to click on object \u0027Object Repository/NewActivity_Object_Repository/textarea_form-control ng-untou\u0027 (Root cause: com.kms.katalon.core.webui.exception.WebElementNotFoundException: Web element with id: \u0027Object Repository/NewActivity_Object_Repository/textarea_form-control ng-untou\u0027 located by \u0027By.xpath: //*[@class \u003d \u0027form-control ng-untouched ng-valid ng-dirty ng-valid-parse\u0027]\u0027 not found)","startTime":1530036777647,"endTime":0,"childRecords":[],"interuppted":false}],"interuppted":false}],"interuppted":false}